setup.py
django_park_keeper.egg-info/PKG-INFO
django_park_keeper.egg-info/SOURCES.txt
django_park_keeper.egg-info/dependency_links.txt
django_park_keeper.egg-info/requires.txt
django_park_keeper.egg-info/top_level.txt
parkkeeper/__init__.py
parkkeeper/admin.py
parkkeeper/base.py
parkkeeper/const.py
parkkeeper/event.py
parkkeeper/factories.py
parkkeeper/forms.py
parkkeeper/models.py
parkkeeper/serializers.py
parkkeeper/signals.py
parkkeeper/task_generator.py
parkkeeper/task_result_collector.py
parkkeeper/urls.py
parkkeeper/utils.py
parkkeeper/views.py
parkkeeper/worker_processor.py
parkkeeper/ws.py
parkkeeper/datatools/__init__.py
parkkeeper/datatools/task.py
parkkeeper/datatools/worker.py
parkkeeper/management/__init__.py
parkkeeper/management/commands/__init__.py
parkkeeper/management/commands/ahttp.py
parkkeeper/management/commands/keep.py
parkkeeper/migrations/0001_initial.py
parkkeeper/migrations/0002_auto_20151102_1401.py
parkkeeper/migrations/0003_auto_20151103_1330.py
parkkeeper/migrations/0004_auto_20151103_1726.py
parkkeeper/migrations/0005_auto_20151108_1008.py
parkkeeper/migrations/0006_auto_20151115_1303.py
parkkeeper/migrations/0007_auto_20151207_0812.py
parkkeeper/migrations/__init__.py