Metadata-Version: 1.0
Name: django-park-keeper
Version: 0.1.5
Summary: Monitoring and services administration.
Home-page: https://github.com/telminov/django-park-keeper
Author: Telminov Sergey
Author-email: UNKNOWN
License: The MIT License
Platform: UNKNOWN
